inventree_niimbot/__init__.py
inventree_niimbot/niimbot_plugin.py
inventree_niimbot/version.py
inventree_niimbot/nimmy/__init__.py
inventree_niimbot/nimmy/bluetooth.py
inventree_niimbot/nimmy/exception.py
inventree_niimbot/nimmy/logger_config.py
inventree_niimbot/nimmy/packet.py
inventree_niimbot/nimmy/printer.py
inventree_niimbot_plugin-0.1.0.dist-info/LICENSE
inventree_niimbot_plugin-0.1.0.dist-info/METADATA
inventree_niimbot_plugin-0.1.0.dist-info/WHEEL
inventree_niimbot_plugin-0.1.0.dist-info/entry_points.txt
inventree_niimbot_plugin-0.1.0.dist-info/top_level.txt
inventree_niimbot_plugin-0.1.0.dist-info/RECORD
