Metadata-Version: 2.1
Name: inventree-niimbot-plugin
Version: 0.1.0
Summary: Niimbot label printer (b1, b18, b21, d11, d110) plugin for InvenTree
Home-page: https://github.com/piramja/inventree-niimbot-plugin
Author: piramja
Author-email: info@piramja.de
License: MIT
Keywords: inventree inventreeplugins label printer printing inventory
Requires-Python: >=3.9
License-File: LICENSE
Requires-Dist: bleak==0.21.1
Requires-Dist: devtools==0.12.2
Requires-Dist: setuptools==69.5.1
Requires-Dist: markdown-it-py==3.0.0
Requires-Dist: loguru==0.7.2
Requires-Dist: pillow==10.3.0
